<?xml version="1.0" encoding="UTF-8"?>
<edu.tigers.sumatra.wp.data.Geometry base="edu.tigers.sumatra.wp.data.Geometry">
    <ballModelIdentifier:GRSIM>grSim</ballModelIdentifier:GRSIM>
    <ballModelIdentifier:SUMATRA>sumatra</ballModelIdentifier:SUMATRA>
    <ballModelIdentifier:LAB>lab</ballModelIdentifier:LAB>
    <ballModelIdentifier:TISCH>lab</ballModelIdentifier:TISCH>
    <ballModelIdentifier:ROBOCUP>default</ballModelIdentifier:ROBOCUP>
    <ballRadius>21.5</ballRadius>
    <botRadius>90.0</botRadius>
    <botToBallDistanceStop>500.0</botToBallDistanceStop>
    <boundaryLength:GRSIM>350.0</boundaryLength:GRSIM>
    <boundaryLength:SUMATRA>350.0</boundaryLength:SUMATRA>
    <boundaryLength:LAB>200</boundaryLength:LAB>
    <boundaryLength:TISCH>100</boundaryLength:TISCH>
    <boundaryLength:ROBOCUP>350.0</boundaryLength:ROBOCUP>
    <boundaryOffset:GRSIM>0.0</boundaryOffset:GRSIM>
    <boundaryOffset:SUMATRA>0.0</boundaryOffset:SUMATRA>
    <boundaryOffset:LAB>0.0</boundaryOffset:LAB>
    <boundaryOffset:TISCH>0.0</boundaryOffset:TISCH>
    <boundaryOffset:ROBOCUP>0.0</boundaryOffset:ROBOCUP>
    <boundaryWidth:GRSIM>350.0</boundaryWidth:GRSIM>
    <boundaryWidth:SUMATRA>350.0</boundaryWidth:SUMATRA>
    <boundaryWidth:LAB>200</boundaryWidth:LAB>
    <boundaryWidth:TISCH>100</boundaryWidth:TISCH>
    <boundaryWidth:ROBOCUP>350</boundaryWidth:ROBOCUP>
    <cameraFocalLength>553.21814;590.2652;500.0;500.0</cameraFocalLength>
    <cameraHeights>3000.0;3000.0;3000.0;3000.0</cameraHeights>
    <cameraPrincipalPointX>378.83185;421.52823;390.0;390.0</cameraPrincipalPointX>
    <cameraPrincipalPointY>303.8912;299.39786;290.0;290.0</cameraPrincipalPointY>
    <center2DribblerDistDefault>75.0</center2DribblerDistDefault>
    <centerCircleRadius:GRSIM>500.0</centerCircleRadius:GRSIM>
    <centerCircleRadius:SUMATRA>500.0</centerCircleRadius:SUMATRA>
    <centerCircleRadius:LAB>500</centerCircleRadius:LAB>
    <centerCircleRadius:TISCH>500.0</centerCircleRadius:TISCH>
    <centerCircleRadius:ROBOCUP>500.0</centerCircleRadius:ROBOCUP>
    <distancePenaltyMarkToPenaltyLine>400.0</distancePenaltyMarkToPenaltyLine>
    <distanceToPenaltyArea:GRSIM>1000.0</distanceToPenaltyArea:GRSIM>
    <distanceToPenaltyArea:SUMATRA>1000.0</distanceToPenaltyArea:SUMATRA>
    <distanceToPenaltyArea:LAB>800</distanceToPenaltyArea:LAB>
    <distanceToPenaltyArea:TISCH>320</distanceToPenaltyArea:TISCH>
    <distanceToPenaltyArea:ROBOCUP>1000.0</distanceToPenaltyArea:ROBOCUP>
    <distanceToPenaltyMark:GRSIM>1000.0</distanceToPenaltyMark:GRSIM>
    <distanceToPenaltyMark:SUMATRA>1000.0</distanceToPenaltyMark:SUMATRA>
    <distanceToPenaltyMark:LAB>750</distanceToPenaltyMark:LAB>
    <distanceToPenaltyMark:TISCH>300</distanceToPenaltyMark:TISCH>
    <distanceToPenaltyMark:ROBOCUP>1000.0</distanceToPenaltyMark:ROBOCUP>
    <fieldLength:GRSIM>8090.0</fieldLength:GRSIM>
    <fieldLength:SUMATRA>9090.0</fieldLength:SUMATRA>
    <fieldLength:LAB>6050</fieldLength:LAB>
    <fieldLength:TISCH>3260</fieldLength:TISCH>
    <fieldLength:ROBOCUP>8090.0</fieldLength:ROBOCUP>
    <fieldWidth:GRSIM>6050.0</fieldWidth:GRSIM>
    <fieldWidth:SUMATRA>6050.0</fieldWidth:SUMATRA>
    <fieldWidth:LAB>4050</fieldWidth:LAB>
    <fieldWidth:TISCH>2370</fieldWidth:TISCH>
    <fieldWidth:ROBOCUP>6050.0</fieldWidth:ROBOCUP>
    <goalDepth>180.0</goalDepth>
    <goalSize:GRSIM>1000.0</goalSize:GRSIM>
    <goalSize:SUMATRA>1000.0</goalSize:SUMATRA>
    <goalSize:LAB>700</goalSize:LAB>
    <goalSize:TISCH>700.0</goalSize:TISCH>
    <goalSize:ROBOCUP>1000.0</goalSize:ROBOCUP>
    <judgesBorderLength:GRSIM>425.0</judgesBorderLength:GRSIM>
    <judgesBorderLength:SUMATRA>425.0</judgesBorderLength:SUMATRA>
    <judgesBorderLength:LAB>425.0</judgesBorderLength:LAB>
    <judgesBorderLength:TISCH>100</judgesBorderLength:TISCH>
    <judgesBorderLength:ROBOCUP>425.0</judgesBorderLength:ROBOCUP>
    <judgesBorderWidth:GRSIM>425.0</judgesBorderWidth:GRSIM>
    <judgesBorderWidth:SUMATRA>425.0</judgesBorderWidth:SUMATRA>
    <judgesBorderWidth:LAB>425.0</judgesBorderWidth:LAB>
    <judgesBorderWidth:TISCH>100</judgesBorderWidth:TISCH>
    <judgesBorderWidth:ROBOCUP>425.0</judgesBorderWidth:ROBOCUP>
    <lengthOfPenaltyAreaFrontLine:GRSIM>500.0</lengthOfPenaltyAreaFrontLine:GRSIM>
    <lengthOfPenaltyAreaFrontLine:SUMATRA>500.0</lengthOfPenaltyAreaFrontLine:SUMATRA>
    <lengthOfPenaltyAreaFrontLine:LAB>350</lengthOfPenaltyAreaFrontLine:LAB>
    <lengthOfPenaltyAreaFrontLine:TISCH>600</lengthOfPenaltyAreaFrontLine:TISCH>
    <lengthOfPenaltyAreaFrontLine:ROBOCUP>500.0</lengthOfPenaltyAreaFrontLine:ROBOCUP>
    <penaltyAreaMargin>100.0</penaltyAreaMargin>
    <receiveGeometry>true</receiveGeometry>
    <stopSpeed>1.5</stopSpeed>
</edu.tigers.sumatra.wp.data.Geometry>
